friendly_sequences-1.13.dist-info/METADATA
friendly_sequences-1.13.dist-info/WHEEL
friendly_sequences-1.13.dist-info/entry_points.txt
friendly_sequences-1.13.dist-info/licenses/LICENSE
friendly_sequences/__init__.py
friendly_sequences/py.typed
friendly_sequences-1.13.dist-info/RECORD
