Metadata-Version: 2.1
Name: friendly-sequences
Version: 1.13
Summary: Friendly sequences made in Python with :love:
Author-Email: zhukovgreen <iam+friendly-sequences@zhukovgreen.pro>
Project-URL: repository, https://github.com/zhukovgreen/friendly-sequences
Requires-Python: >=3.10
Requires-Dist: attrs>=21.3.0
